{
"type": "FeatureCollection",
"name": "matterport",
"crs": { "type": "name", "properties": { "name": "urn:ogc:def:crs:OGC:1.3:CRS84" } },
"features": [
{ "type": "Feature", "properties": { "site": "Melbourne Town Hall", "matterport_link": "<iframe src='https://my.matterport.com/show/?play=1&lang=de&m=Knyns6QdBEo' allowfullscreen></iframe>" }, "geometry": { "type": "Point", "coordinates": [ 144.966664632161439, -37.815027046203632, 40.0 ] } },
{ "type": "Feature", "properties": { "site": "St Paul's Cathedral", "matterport_link": "<iframe src='https://my.matterport.com/show/?play=1&lang=en-US&m=dhjEzFoUFzH' allowfullscreen></iframe>" }, "geometry": { "type": "Point", "coordinates": [ 144.967544881194215, -37.816633217906229, 100.0 ] } },
{ "type": "Feature", "properties": { "site": "RACV City Club", "matterport_link": "<iframe src='https://my.matterport.com/show/?play=1&lang=en-US&m=z4G2MEULNsj' allowfullscreen></iframe>" }, "geometry": { "type": "Point", "coordinates": [ 144.959546392726253, -37.815763837587554, 120.0 ] } }
]
}
